setup.py
Flask_RegisterBlueprints.egg-info/PKG-INFO
Flask_RegisterBlueprints.egg-info/SOURCES.txt
Flask_RegisterBlueprints.egg-info/dependency_links.txt
Flask_RegisterBlueprints.egg-info/not-zip-safe
Flask_RegisterBlueprints.egg-info/top_level.txt
flask_registerblueprints/__init__.py
flask_registerblueprints/exceptions.py
flask_registerblueprints/register.py