Metadata-Version: 1.1
Name: Flask-RegisterBlueprints
Version: 0.1.0
Summary: Dynamically register Flask blueprints on application object
Home-page: https://github.com/joelcolucci/flask-registerblueprints
Author: Joel Colucci
Author-email: joelcolucci@gmail.com
License: MIT
Platform: any
Classifier: Environment :: Web Environment
Classifier: Intended Audience :: Developers
Classifier: License :: OSI Approved :: MIT License
Classifier: Operating System :: OS Independent
Classifier: Programming Language :: Python
Classifier: Topic :: Internet :: WWW/HTTP :: Dynamic Content
Classifier: Topic :: Software Development :: Libraries :: Python Modules
